{"key":"cache\/stash_default\/prov\/elementlist\/64b03b33f0089f2d0f3042b71546d2fe\/","data":{"return":{"23":{"element_id":"23","parent_id":null,"hier_element_id":"23","element_code":"description","documentation_url":"","datatype":"1","list_id":null,"settings":{"usewysiwygeditor":"1","fieldWidth":"640px","fieldHeight":"6","minChars":"0","maxChars":"65535"},"rank":"0","deleted":"0","hier_left":"1.00000000000000000000","hier_right":"4294967296.00000000000000000000","display_label":"Description"},"24":{"element_id":"24","parent_id":null,"hier_element_id":"24","element_code":"description_source","documentation_url":"","datatype":"1","list_id":null,"settings":{"fieldWidth":"640px","fieldHeight":"3","minChars":"0","maxChars":"65535"},"rank":"0","deleted":"0","hier_left":"1.00000000000000000000","hier_right":"4294967296.00000000000000000000","display_label":"Source of description"},"29":{"element_id":"29","parent_id":null,"hier_element_id":"29","element_code":"external_link","documentation_url":"","datatype":"0","list_id":null,"settings":{"doesNotTakeLocale":"1"},"rank":"0","deleted":"0","hier_left":"1.00000000000000000000","hier_right":"4294967296.00000000000000000000","display_label":"External links"},"34":{"element_id":"34","parent_id":null,"hier_element_id":"34","element_code":"internal_notes","documentation_url":"","datatype":"1","list_id":null,"settings":{"fieldWidth":"70","fieldHeight":"4","minChars":"0","maxChars":"65535","doesNotTakeLocale":"1"},"rank":"0","deleted":"0","hier_left":"1.00000000000000000000","hier_right":"4294967296.00000000000000000000","display_label":"Notes (internal use only)"},"48":{"element_id":"48","parent_id":null,"hier_element_id":"48","element_code":"lcsh_terms","documentation_url":"","datatype":"13","list_id":null,"settings":{"fieldWidth":"500px","fieldHeight":"1"},"rank":"0","deleted":"0","hier_left":"1.00000000000000000000","hier_right":"4294967296.00000000000000000000","display_label":"Library of Congress Subject Headings"}},"createdOn":1779381998},"expiration":1779385366}