{"key":"cache\/stash_default\/prov\/localelist\/name_asc_1_0_0\/","data":{"return":{"cs_CZ":{"locale_id":"9","name":"Czech","language":"cs","country":"CZ","dialect":null,"dont_use_for_cataloguing":"1","code":"cs_CZ"},"de_DE":{"locale_id":"5","name":"Deutsch (Deutschland)","language":"de","country":"DE","dialect":null,"dont_use_for_cataloguing":"1","code":"de_DE"},"de_AT":{"locale_id":"6","name":"Deutsch (\u00d6sterreich)","language":"de","country":"AT","dialect":null,"dont_use_for_cataloguing":"1","code":"de_AT"},"en_US":{"locale_id":"1","name":"English","language":"en","country":"US","dialect":null,"dont_use_for_cataloguing":"0","code":"en_US"},"en_AU":{"locale_id":"3","name":"English (Australian)","language":"en","country":"AU","dialect":null,"dont_use_for_cataloguing":"1","code":"en_AU"},"en_CA":{"locale_id":"2","name":"English (Canadian)","language":"en","country":"CA","dialect":null,"dont_use_for_cataloguing":"1","code":"en_CA"},"en_GB":{"locale_id":"4","name":"English (UK)","language":"en","country":"GB","dialect":null,"dont_use_for_cataloguing":"1","code":"en_GB"},"es_ES":{"locale_id":"10","name":"Espa\u00f1ol","language":"es","country":"ES","dialect":null,"dont_use_for_cataloguing":"1","code":"es_ES"},"fr_FR":{"locale_id":"7","name":"Fran\u00e7ais","language":"fr","country":"FR","dialect":null,"dont_use_for_cataloguing":"1","code":"fr_FR"},"fr_CA":{"locale_id":"8","name":"Fran\u00e7ais (Canadien)","language":"fr","country":"CA","dialect":null,"dont_use_for_cataloguing":"1","code":"fr_CA"},"it_IT":{"locale_id":"11","name":"Italiano","language":"it","country":"IT","dialect":null,"dont_use_for_cataloguing":"1","code":"it_IT"},"nl_NL":{"locale_id":"12","name":"Nederlands","language":"nl","country":"NL","dialect":null,"dont_use_for_cataloguing":"1","code":"nl_NL"},"sv_SE":{"locale_id":"13","name":"Svenska","language":"sv","country":"SE","dialect":null,"dont_use_for_cataloguing":"1","code":"sv_SE"}},"createdOn":1779734320},"expiration":1779737610}